action_logger/__init__.py
action_logger/client.py
action_logger/external_link.py
action_logger/link_solver.py
action_logger-1.0.12.dist-info/LICENSE
action_logger-1.0.12.dist-info/METADATA
action_logger-1.0.12.dist-info/WHEEL
action_logger-1.0.12.dist-info/top_level.txt
action_logger-1.0.12.dist-info/RECORD
