Metadata-Version: 2.1
Name: action-logger
Version: 1.0.12
Summary: Action logger for digital transformer
Author: TimeAshore
Author-email: timeashore@163.com
License: UNKNOWN
Platform: UNKNOWN
Classifier: Programming Language :: Python :: 3
Classifier: License :: OSI Approved :: MIT License
Classifier: Operating System :: OS Independent
Requires-Python: >=3.6
License-File: LICENSE
Requires-Dist: aiohttp
Requires-Dist: python-dotenv (==0.19.1)
Requires-Dist: flask
Requires-Dist: requests
